markowitz/__init__.py
markowitz/gui.py
markowitz/steps.py
markowitz-0.1.0.dist-info/METADATA
markowitz-0.1.0.dist-info/WHEEL
markowitz-0.1.0.dist-info/top_level.txt
markowitz-0.1.0.dist-info/RECORD
