Metadata-Version: 2.1
Name: markowitz
Version: 0.1.0
Summary: Librería educativa para enseñar el modelo de Markowitz paso a paso
Author: Jesús Colbert
Requires-Python: >=3.9
Requires-Dist: pandas
Requires-Dist: numpy
Requires-Dist: yfinance
Requires-Dist: matplotlib
Requires-Dist: PyQt5
Requires-Dist: openpyxl
